210905094_Harshit_DSD A1/lab 2/l2q1b.v
module l2q1b(a,b,c,d,f1,f2);
input a,b,c,d;
output f1,f2;
and(k1,b,~c,~d);
and(k2,d,~b);
and(k3,c,~b);
or(f1,k1,k2,k3);
assign f2=((b&~c)&~d)|(d&~b)|(c&~b);
endmodule

210905094_Harshit_DSD A1/lab 2/l2q1b_tb.v
`timescale 1ns/1ns
`include "l2q1b.v"
module l2q1b_tb();
reg a,b,c,d;
wire f1,f2;
l2q1b llq(a,b,c,d,f1,f2);
initial
begin
$dumpfile("l2q1b_tb.vcd");
$dumpvars(0,l2q1b_tb);
a=0;b=0;c=0;d=0;
#20;
a=0;b=0;c=0;d=1;
#20;
a=0;b=0;c=1;d=0;
#20;
a=0;b=0;c=1;d=1;
#20;
a=0;b=1;c=0;d=0;
#20;
a=0;b=1;c=0;d=1;
#20;
a=0;b=1;c=1;d=0;
#20;
a=0;b=1;c=1;d=1;
#20;
a=1;b=0;c=0;d=0;
#20;
a=1;b=0;c=0;d=1;
#20;
a=1;b=0;c=1;d=0;
#20;
a=1;b=0;c=1;d=1;
#20;
a=1;b=1;c=0;d=0;
#20;
a=1;b=1;c=0;d=1;
#20;
a=1;b=1;c=1;d=0;
#20;
a=1;b=1;c=1;d=1;
#20;
$display("Test complete");
end
endmodule

210905094_Harshit_DSD A1/lab 2/l2q1b_tb.vcd
$date
	Thu Sep  1 15:57:55 2022
$end
$version
	Icarus Verilog
$end
$timescale
	1ns
$end
$scope module l2q1b_tb $end
$var wire 1 ! f2 $end
$var wire 1 " f1 $end
$var reg 1 # a $end
$var reg 1 $ b $end
$var reg 1 % c $end
$var reg 1 & d $end
$scope module llq $end
$var wire 1 # a $end
$var wire 1 $ b $end
$var wire 1 % c $end
$var wire 1 & d $end
$var wire 1 " f1 $end
$var wire 1 ! f2 $end
$var wire 1 ' k1 $end
$var wire 1 ( k2 $end
$var wire 1 ) k3 $end
$upscope $end
$upscope $end
$enddefinitions $end
#0
$dumpvars
0)
0(
0'
0&
0%
0$
0#
0"
0!
$end
#20
1!
1"
1(
1&
#40
0(
1)
0&
1%
#60
1(
1&
#80
1!
1'
1"
0(
0)
0&
0%
1$
#100
0!
0"
0'
1&
#120
0&
1%
#140
1&
#160
0&
0%
0$
1#
#180
1!
1"
1(
1&
#200
0(
1)
0&
1%
#220
1(
1&
#240
1!
1'
1"
0(
0)
0&
0%
1$
#260
0!
0"
0'
1&
#280
0&
1%
#300
1&
