210905094_Harshit_DSD A1/lab 3/prog4.v
module prog4(x1,x2,x3,f);
input x1,x2,x3;
output f;
assign f = (x1&x2)|(x2&x3)|(x3&x1);
endmodule

210905094_Harshit_DSD A1/lab 3/prog4_tb.v
`timescale 1ns/1ns
`include "prog4.v"

module prog4_tb;
reg x1, x2, x3;

wire f;

prog4 pb4(x1, x2, x3, f); 
initial
begin
$dumpfile("prog4_tb.vcd");
$dumpvars(0, prog4_tb);
x1=1'b0; x2=1'b0; x3=1'b0;
#20;
x1=1'b0; x2=1'b0; x3=1'b1;
#20;
x1=1'b0; x2=1'b1; x3=1'b0;
#20;
x1=1'b0; x2=1'b1; x3=1'b1;
#20;
x1=1'b1; x2=1'b0; x3=1'b0;
#20;
x1=1'b1; x2=1'b0; x3=1'b1;
#20;
x1=1'b1; x2=1'b1; x3=1'b0;
#20;
x1=1'b1; x2=1'b1; x3=1'b1;
#20;
$display("Test complete");
end
endmodule

210905094_Harshit_DSD A1/lab 3/prog4_tb.vcd
$date
	Mon Sep  5 15:10:49 2022
$end
$version
	Icarus Verilog
$end
$timescale
	1ns
$end
$scope module prog4_tb $end
$var wire 1 ! f $end
$var reg 1 " x1 $end
$var reg 1 # x2 $end
$var reg 1 $ x3 $end
$scope module pb4 $end
$var wire 1 ! f $end
$var wire 1 " x1 $end
$var wire 1 # x2 $end
$var wire 1 $ x3 $end
$upscope $end
$upscope $end
$enddefinitions $end
#0
$dumpvars
0$
0#
0"
0!
$end
#20
1$
#40
0$
1#
#60
1!
1$
#80
0!
0$
0#
1"
#100
1!
1$
#120
0$
1#
#140
1$
