210905094_Harshit_DSD A1/lab 3/prog2.v
module prog2(a,b,c,d,f);
input a,b,c,d;
output f;
assign f = (~b&~d)|(c&~d)|(a&b&~c&d);
endmodule

210905094_Harshit_DSD A1/lab 3/prog2_tb.v
`timescale 1ns/1ns
`include "prog2.v"

module prog2_tb;
reg a,b,c,d;
wire f;

prog2 pb2(a,b,c,d,f);
initial begin

	$dumpfile("prog2_tb.vcd");
	$dumpvars(0,prog2_tb);
	
	a=0;b=0;c=0;d=0;
	#10;
	
	a=0;b=0;c=0;d=1;
	#10;
	
	a=0;b=0;c=1;d=0;
	#10;
	
	a=0;b=0;c=1;d=1;
	#10;
	
	a=0;b=1;c=0;d=0;
	#10;
	
	a=0;b=1;c=0;d=1;
	#10;
	
	a=0;b=1;c=1;d=0;
	#10;
	
	a=0;b=1;c=1;d=1;
	#10;
	
	a=1;b=0;c=0;d=0;
	#10;
	
	a=1;b=0;c=0;d=1;
	#10;
	
	a=1;b=0;c=1;d=0;
	#10;
	
	a=1;b=0;c=1;d=1;
	#10;
	
	a=1;b=1;c=0;d=0;
	#10;
	
	a=1;b=1;c=0;d=1;
	#10;
	
	a=1;b=1;c=1;d=0;
	#10;
	
	a=1;b=1;c=1;d=1;
	#10;
	
	$display("Test complete");
	
end

endmodule

210905094_Harshit_DSD A1/lab 3/prog2_tb.vcd
$date
	Mon Sep  5 14:46:22 2022
$end
$version
	Icarus Verilog
$end
$timescale
	1ns
$end
$scope module prog2_tb $end
$var wire 1 ! f $end
$var reg 1 " a $end
$var reg 1 # b $end
$var reg 1 $ c $end
$var reg 1 % d $end
$scope module pb2 $end
$var wire 1 " a $end
$var wire 1 # b $end
$var wire 1 $ c $end
$var wire 1 % d $end
$var wire 1 ! f $end
$upscope $end
$upscope $end
$enddefinitions $end
#0
$dumpvars
0%
0$
0#
0"
1!
$end
#10
0!
1%
#20
1!
0%
1$
#30
0!
1%
#40
0%
0$
1#
#50
1%
#60
1!
0%
1$
#70
0!
1%
#80
1!
0%
0$
0#
1"
#90
0!
1%
#100
1!
0%
1$
#110
0!
1%
#120
0%
0$
1#
#130
1!
1%
#140
1!
0%
1$
#150
0!
1%
