210905094_Harshit_DSD A1/lab 3/prog3.v
module prog3(a,b,c,d,f);
input a,b,c,d;
output f;
assign f = (b|d)&(~a|b)&(a|~c|~d)&(~a|c|~d);
endmodule

210905094_Harshit_DSD A1/lab 3/prog3_tb.v
`timescale 1ns/1ns
`include "prog3.v"

module prog3_tb;
reg a,b,c,d;
wire f;

prog3 pb3(a,b,c,d,f);
initial begin

	$dumpfile("prog3_tb.vcd");
	$dumpvars(0,prog3_tb);
	
	a=0;b=0;c=0;d=0;
	#10;
	
	a=0;b=0;c=0;d=1;
	#10;
	
	a=0;b=0;c=1;d=0;
	#10;
	
	a=0;b=0;c=1;d=1;
	#10;
	
	a=0;b=1;c=0;d=0;
	#10;
	
	a=0;b=1;c=0;d=1;
	#10;
	
	a=0;b=1;c=1;d=0;
	#10;
	
	a=0;b=1;c=1;d=1;
	#10;
	
	a=1;b=0;c=0;d=0;
	#10;
	
	a=1;b=0;c=0;d=1;
	#10;
	
	a=1;b=0;c=1;d=0;
	#10;
	
	a=1;b=0;c=1;d=1;
	#10;
	
	a=1;b=1;c=0;d=0;
	#10;
	
	a=1;b=1;c=0;d=1;
	#10;
	
	a=1;b=1;c=1;d=0;
	#10;
	
	a=1;b=1;c=1;d=1;
	#10;
	
	$display("Test complete");
	
end

endmodule

210905094_Harshit_DSD A1/lab 3/prog3_tb.vcd
$date
	Mon Sep  5 14:59:18 2022
$end
$version
	Icarus Verilog
$end
$timescale
	1ns
$end
$scope module prog3_tb $end
$var wire 1 ! f $end
$var reg 1 " a $end
$var reg 1 # b $end
$var reg 1 $ c $end
$var reg 1 % d $end
$scope module pb3 $end
$var wire 1 " a $end
$var wire 1 # b $end
$var wire 1 $ c $end
$var wire 1 % d $end
$var wire 1 ! f $end
$upscope $end
$upscope $end
$enddefinitions $end
#0
$dumpvars
0%
0$
0#
0"
0!
$end
#10
1!
1%
#20
0!
0%
1$
#30
1%
#40
1!
0%
0$
1#
#50
1%
#60
0%
1$
#70
0!
1%
#80
0%
0$
0#
1"
#90
1%
#100
0%
1$
#110
1%
#120
1!
0%
0$
1#
#130
0!
1%
#140
1!
0%
1$
#150
1%
