210905094_Harshit_DSD A1/lab 7/l7q4.v
module l7q4(b,g);
input [3:0]b;
output [3:0]g;
fourtoone stage0({4{b[1]^b[0]}},b[3:2],g[0]);
fourtoone stage1({~b[1],b[1],~b[1],b[1]},b[3:2],g[1]);
fourtoone stage2({1'b0,1'b1,1'b1,1'b0},b[3:2],g[2]);
fourtoone stage3({1'b1,1'b1,1'b0,1'b0},b[3:2],g[3]);
endmodule
module fourtoone(i,s,f);
input [3:0]i;
input [1:0]s;
output f;
reg f;
always @(i,s)
begin
f = s[1]?(s[0]?i[3]:i[2]):(s[0]?i[1]:i[0]);
end
endmodule

210905094_Harshit_DSD A1/lab 7/l7q4_tb.v
`timescale 1ns/1ns
`include "l7q4.v"

module l7q4_tb();
reg [3:0] b;
wire [3:0] g;

l7q4 foo(b,g);
initial begin
        $dumpfile("l7q4_tb.vcd");
        $dumpvars(0,l7q4_tb);
        
        b=4'b0000;#20;
        b=4'b0001;#20;
        b=4'b0010;#20;
        b=4'b0011;#20;
        b=4'b0100;#20;
        b=4'b0101;#20;
        b=4'b0110;#20;
        b=4'b0111;#20;
        b=4'b1000;#20;
        b=4'b1001;#20;
        b=4'b1010;#20;
        b=4'b1011;#20;
        b=4'b1100;#20;
        b=4'b1101;#20;
        b=4'b1110;#20;
        b=4'b1111;#20;
        
        $display("test Complete");
end
endmodule

210905094_Harshit_DSD A1/lab 7/l7q4_tb.vcd
$date
	Thu Oct 20 16:05:40 2022
$end
$version
	Icarus Verilog
$end
$timescale
	1ns
$end
$scope module l7q4_tb $end
$var wire 4 ! g [3:0] $end
$var reg 4 " b [3:0] $end
$scope module foo $end
$var wire 4 # b [3:0] $end
$var wire 4 $ g [3:0] $end
$scope module stage0 $end
$var wire 4 % i [3:0] $end
$var wire 2 & s [1:0] $end
$var reg 1 ' f $end
$upscope $end
$scope module stage1 $end
$var wire 4 ( i [3:0] $end
$var wire 2 ) s [1:0] $end
$var reg 1 * f $end
$upscope $end
$scope module stage2 $end
$var wire 4 + i [3:0] $end
$var wire 2 , s [1:0] $end
$var reg 1 - f $end
$upscope $end
$scope module stage3 $end
$var wire 4 . i [3:0] $end
$var wire 2 / s [1:0] $end
$var reg 1 0 f $end
$upscope $end
$upscope $end
$upscope $end
$enddefinitions $end
#0
$dumpvars
00
b0 /
b1100 .
0-
b0 ,
b110 +
0*
b0 )
b1010 (
0'
b0 &
b0 %
b0 $
b0 #
b0 "
b0 !
$end
#20
b1 !
b1 $
1'
b1111 %
b1 "
b1 #
#40
b11 !
b11 $
1*
b101 (
b10 "
b10 #
#60
b10 !
b10 $
0'
b0 %
b11 "
b11 #
#80
1*
b110 !
b110 $
1-
b1 &
b1010 (
b1 )
b1 ,
b1 /
b100 "
b100 #
#100
b111 !
b111 $
1'
b1111 %
b101 "
b101 #
#120
b101 !
b101 $
0*
b101 (
b110 "
b110 #
#140
b100 !
b100 $
0'
b0 %
b111 "
b111 #
#160
b1100 !
b1100 $
10
b10 &
b1010 (
b10 )
b10 ,
b10 /
b1000 "
b1000 #
#180
b1101 !
b1101 $
1'
b1111 %
b1001 "
b1001 #
#200
b1111 !
b1111 $
1*
b101 (
b1010 "
b1010 #
#220
b1110 !
b1110 $
0'
b0 %
b1011 "
b1011 #
#240
1*
b1010 !
b1010 $
0-
b11 &
b1010 (
b11 )
b11 ,
b11 /
b1100 "
b1100 #
#260
b1011 !
b1011 $
1'
b1111 %
b1101 "
b1101 #
#280
b1001 !
b1001 $
0*
b101 (
b1110 "
b1110 #
#300
b1000 !
b1000 $
0'
b0 %
b1111 "
b1111 #
