210905094_Harshit_DSD A1/lab 1/problem1.v
module problem1(a,b,c,d,f);
	input a,b,c,d;
	output f;
	assign f=((~((a&b)|c))&d)&(((a&b)|c)|d);
endmodule

210905094_Harshit_DSD A1/lab 1/problem1_tb.v
`timescale 1ns/1ns
`include "problem1.v"

module problem1_tb;
reg a,b,c,d;
wire f;

problem1 pb1(a,b,c,d,f);
initial begin

	$dumpfile("problem1_tb.vcd");
	$dumpvars(0,problem1_tb);
	
	a=0;b=0;c=0;d=0;
	#10;
	
	a=0;b=0;c=0;d=1;
	#10;
	
	a=0;b=0;c=1;d=0;
	#10;
	
	a=0;b=0;c=1;d=1;
	#10;
	
	a=0;b=1;c=0;d=0;
	#10;
	
	a=0;b=1;c=0;d=1;
	#10;
	
	a=0;b=1;c=1;d=0;
	#10;
	
	a=0;b=1;c=1;d=1;
	#10;
	
	a=1;b=0;c=0;d=0;
	#10;
	
	a=1;b=0;c=0;d=1;
	#10;
	
	a=1;b=0;c=1;d=0;
	#10;
	
	a=1;b=0;c=1;d=1;
	#10;
	
	a=1;b=1;c=0;d=0;
	#10;
	
	a=1;b=1;c=0;d=1;
	#10;
	
	a=1;b=1;c=1;d=0;
	#10;
	
	a=1;b=1;c=1;d=1;
	#10;
	
	$display("Test complete");
	
end

endmodule

210905094_Harshit_DSD A1/lab 1/problem1_tb.vcd
$date
	Thu Aug 18 16:15:08 2022
$end
$version
	Icarus Verilog
$end
$timescale
	1ns
$end
$scope module problem1_tb $end
$var wire 1 ! f $end
$var reg 1 " a $end
$var reg 1 # b $end
$var reg 1 $ c $end
$var reg 1 % d $end
$scope module pb1 $end
$var wire 1 " a $end
$var wire 1 # b $end
$var wire 1 $ c $end
$var wire 1 % d $end
$var wire 1 ! f $end
$upscope $end
$upscope $end
$enddefinitions $end
#0
$dumpvars
0%
0$
0#
0"
0!
$end
#10
1!
1%
#20
0!
0%
1$
#30
1%
#40
0%
0$
1#
#50
1!
1%
#60
0!
0%
1$
#70
1%
#80
0%
0$
0#
1"
#90
1!
1%
#100
0!
0%
1$
#110
1%
#120
0%
0$
1#
#130
1%
#140
0%
1$
#150
1%
